daa.pyi
daa.cpython-36m-x86_64-linux-gnu.so
daa-1.4.2.dist-info/RECORD
daa-1.4.2.dist-info/WHEEL
daa-1.4.2.dist-info/top_level.txt
daa-1.4.2.dist-info/LICENSE-3RD-PARTY
daa-1.4.2.dist-info/METADATA
